examples/__init__.py
hyperts/__init__.py
hyperts/_version.py
hyperts/config.py
hyperts/experiment.py
hyperts/hyper_ts.py
hyperts/toolbox.py
hyperts/datasets/__init__.py
hyperts/datasets/arrow_head.pkl
hyperts/datasets/base.py
hyperts/datasets/basic_motions.pkl
hyperts/datasets/example_air_passengers.csv
hyperts/datasets/example_retail_sales.csv
hyperts/datasets/example_wp_log_R.csv
hyperts/datasets/example_wp_log_R_outliers1.csv
hyperts/datasets/example_wp_log_R_outliers2.csv
hyperts/datasets/example_wp_log_peyton_manning.csv
hyperts/datasets/example_yosemite_temps.csv
hyperts/datasets/network_traffic_forecast.csv
hyperts/datasets/realKnownCause.csv
hyperts/framework/__init__.py
hyperts/framework/compete.py
hyperts/framework/estimators.py
hyperts/framework/dl/__init__.py
hyperts/framework/dl/_base.py
hyperts/framework/dl/dl_utils/__init__.py
hyperts/framework/dl/dl_utils/_utils.py
hyperts/framework/dl/dl_utils/metainfo.py
hyperts/framework/dl/dl_utils/saveconfig.py
hyperts/framework/dl/dl_utils/timeseries.py
hyperts/framework/dl/layers/__init__.py
hyperts/framework/dl/layers/_layers.py
hyperts/framework/dl/losses/__init__.py
hyperts/framework/dl/losses/_losses.py
hyperts/framework/dl/metrics/__init__.py
hyperts/framework/dl/metrics/_metrics.py
hyperts/framework/dl/models/__init__.py
hyperts/framework/dl/models/deepar.py
hyperts/framework/dl/models/hybrid_rnn.py
hyperts/framework/dl/models/inceptiontime.py
hyperts/framework/dl/models/lstnet.py
hyperts/framework/dl/models/nbeats.py
hyperts/framework/dl/models/vae.py
hyperts/framework/dl/optimizers/__init__.py
hyperts/framework/dl/optimizers/_optimizers.py
hyperts/framework/meta_learning/__init__.py
hyperts/framework/meta_learning/helper_fn.py
hyperts/framework/meta_learning/meta_learner.py
hyperts/framework/meta_learning/meta_trial_store.py
hyperts/framework/meta_learning/tsfeatures.py
hyperts/framework/meta_learning/configurations/__init__.py
hyperts/framework/meta_learning/metafeatures/__init__.py
hyperts-0.2.2.dist-info/LICENSE
hyperts-0.2.2.dist-info/METADATA
hyperts-0.2.2.dist-info/WHEEL
hyperts-0.2.2.dist-info/top_level.txt
hyperts-0.2.2.dist-info/RECORD
