Metadata-Version: 2.1
Name: hyperts
Version: 0.2.2
Home-page: https://github.com/DataCanvasIO/HyperTS
Author: DataCanvas Community
Author-email: yangjian@zetyun.com
License: Apache License 2.0
Classifier: Operating System :: OS Independent
Classifier: Intended Audience :: Developers
Classifier: Intended Audience :: Education
Classifier: Intended Audience :: Science/Research
Classifier: Programming Language :: Python
Classifier: Programming Language :: Python :: 3.7
Classifier: Programming Language :: Python :: 3.8
Classifier: Programming Language :: Python :: 3.9
Classifier: Programming Language :: Python :: 3.10
Classifier: Topic :: Scientific/Engineering
Classifier: Topic :: Scientific/Engineering :: Artificial Intelligence
Classifier: Topic :: Software Development
Classifier: Topic :: Software Development :: Libraries
Classifier: Topic :: Software Development :: Libraries :: Python Modules
Requires-Python: >=3.7
License-File: LICENSE
Requires-Dist: hypernets >=0.3.0
Requires-Dist: prophet >=1.0.1
Requires-Dist: statsmodels >=0.12.1
Requires-Dist: numpy >=1.16.5
Requires-Dist: pandas <2.0,>=0.25.3
Requires-Dist: scikit-learn >=0.22.1
Requires-Dist: scipy
Requires-Dist: numba
